kazurator/__init__.py
kazurator/internals.py
kazurator/mutex.py
kazurator/read_write_lock.py
kazurator/utils.py
kazurator/tests/__init__.py
kazurator/tests/test_internals.py
kazurator/tests/test_mutex.py
kazurator/tests/test_read_write_lock.py
kazurator/tests/test_utils.py
kazurator-0.1.1.dist-info/DESCRIPTION.rst
kazurator-0.1.1.dist-info/METADATA
kazurator-0.1.1.dist-info/RECORD
kazurator-0.1.1.dist-info/WHEEL
kazurator-0.1.1.dist-info/metadata.json
kazurator-0.1.1.dist-info/top_level.txt
