Metadata-Version: 2.0
Name: kazurator
Version: 0.1.1
Summary: Inter process lock recipes that play nice with curator
Home-page: https://github.com/pseudomuto/kazurator
Author: David Muto (pseudomuto)
Author-email: david.muto@gmail.com
License: MIT
Keywords: zookeeper lock
Platform: UNKNOWN
Classifier: Development Status :: 4 - Beta
Classifier: License :: OSI Approved :: MIT License
Classifier: Intended Audience :: Developers
Classifier: Operating System :: OS Independent
Classifier: Programming Language :: Python
Classifier: Programming Language :: Python :: 2
Classifier: Programming Language :: Python :: 2.7
Classifier: Programming Language :: Python :: 3
Classifier: Programming Language :: Python :: 3.3
Classifier: Programming Language :: Python :: 3.4
Classifier: Programming Language :: Python :: 3.5
Classifier: Programming Language :: Python :: 3.6
Classifier: Programming Language :: Python :: Implementation :: CPython
Classifier: Programming Language :: Python :: Implementation :: PyPy
Classifier: Topic :: Communications
Classifier: Topic :: System :: Distributed Computing
Classifier: Topic :: System :: Networking
Requires-Dist: kazoo (>=2.0.0)
Provides-Extra: test
Requires-Dist: kazoo (>=2.0.0); extra == 'test'
Requires-Dist: flake8 (>=3.2.1); extra == 'test'
Requires-Dist: nose (>=1.3.7); extra == 'test'
Requires-Dist: pep8 (>=1.7.0); extra == 'test'
Requires-Dist: tox (>=2.3.1); extra == 'test'
